{"nodes": [{"id": "c_programas_3dosim_3dosim_v4_docs_modulo_3_vision_general_md", "label": "vision_general.md", "file_type": "document", "source_file": "C:\\programas\\3Dosim\\3Dosim_v4\\docs\\modulo_3\\vision_general.md", "source_location": "L1"}, {"id": "modulo_3_vision_general_visi\u00f3n_general_m\u00f3dulo_3_dosimetr\u00eda_interna_3d", "label": "Visi\u00f3n General \u2014 M\u00f3dulo 3: Dosimetr\u00eda Interna 3D", "file_type": "document", "source_file": "C:\\programas\\3Dosim\\3Dosim_v4\\docs\\modulo_3\\vision_general.md", "source_location": "L1"}, {"id": "modulo_3_vision_general_acr\u00f3nimos", "label": "Acr\u00f3nimos", "file_type": "document", "source_file": "C:\\programas\\3Dosim\\3Dosim_v4\\docs\\modulo_3\\vision_general.md", "source_location": "L5"}, {"id": "modulo_3_vision_general_1_contexto_cl\u00ednico", "label": "1. Contexto Cl\u00ednico", "file_type": "document", "source_file": "C:\\programas\\3Dosim\\3Dosim_v4\\docs\\modulo_3\\vision_general.md", "source_location": "L28"}, {"id": "modulo_3_vision_general_2_pipeline_de_10_pasos", "label": "2. Pipeline de 10 Pasos", "file_type": "document", "source_file": "C:\\programas\\3Dosim\\3Dosim_v4\\docs\\modulo_3\\vision_general.md", "source_location": "L45"}, {"id": "modulo_3_vision_general_codeblock_1", "label": "code:block1 (\u250c\u2500\u2500\u2500\u2500\u2500\u2500\u2500\u2500\u2500\u2500\u2500\u2500\u2500\u2500\u2500\u2500\u2500\u2500\u2500\u2500\u2500\u2500\u2500\u2500\u2500\u2500\u2500\u2500\u2500\u2500\u2500\u2500\u2500\u2500\u2500\u2500\u2500\u2500\u2500\u2500\u2500\u2500\u2500\u2500\u2500\u2500\u2500\u2500\u2500\u2500\u2500\u2500\u2500\u2500\u2500\u2500\u2500\u2500\u2500)", "file_type": "document", "source_file": "C:\\programas\\3Dosim\\3Dosim_v4\\docs\\modulo_3\\vision_general.md", "source_location": "L49"}, {"id": "modulo_3_vision_general_paso_1_load_scene_cargar_escena_desde_m\u00f3dulo_1", "label": "Paso 1: `load_scene` \u2014 Cargar escena desde M\u00f3dulo 1", "file_type": "document", "source_file": "C:\\programas\\3Dosim\\3Dosim_v4\\docs\\modulo_3\\vision_general.md", "source_location": "L82"}, {"id": "modulo_3_vision_general_paso_2_read_pet_activity_leer_actividad_pet", "label": "Paso 2: `read_pet_activity` \u2014 Leer actividad PET", "file_type": "document", "source_file": "C:\\programas\\3Dosim\\3Dosim_v4\\docs\\modulo_3\\vision_general.md", "source_location": "L90"}, {"id": "modulo_3_vision_general_paso_3_parse_mctal_parsear_archivo_mctal", "label": "Paso 3: `parse_mctal` \u2014 Parsear archivo MCTAL", "file_type": "document", "source_file": "C:\\programas\\3Dosim\\3Dosim_v4\\docs\\modulo_3\\vision_general.md", "source_location": "L94"}, {"id": "modulo_3_vision_general_paso_4_convert_to_dose_convertir_mev_cm3_a_gy", "label": "Paso 4: `convert_to_dose` \u2014 Convertir MeV/cm\u00b3 a Gy", "file_type": "document", "source_file": "C:\\programas\\3Dosim\\3Dosim_v4\\docs\\modulo_3\\vision_general.md", "source_location": "L104"}, {"id": "modulo_3_vision_general_paso_5_compute_dvh_histograma_dosis_volumen", "label": "Paso 5: `compute_dvh` \u2014 Histograma Dosis-Volumen", "file_type": "document", "source_file": "C:\\programas\\3Dosim\\3Dosim_v4\\docs\\modulo_3\\vision_general.md", "source_location": "L114"}, {"id": "modulo_3_vision_general_paso_6_compute_radiobiology_bed_eud_eqd2", "label": "Paso 6: `compute_radiobiology` \u2014 BED, EUD, EQD2", "file_type": "document", "source_file": "C:\\programas\\3Dosim\\3Dosim_v4\\docs\\modulo_3\\vision_general.md", "source_location": "L122"}, {"id": "modulo_3_vision_general_paso_7_mird_partition_modelo_mird_de_partici\u00f3n", "label": "Paso 7: `mird_partition` \u2014 Modelo MIRD de Partici\u00f3n", "file_type": "document", "source_file": "C:\\programas\\3Dosim\\3Dosim_v4\\docs\\modulo_3\\vision_general.md", "source_location": "L132"}, {"id": "modulo_3_vision_general_paso_8_visualize_slicer_visualizaci\u00f3n_en_3d_slicer", "label": "Paso 8: `visualize_slicer` \u2014 Visualizaci\u00f3n en 3D Slicer", "file_type": "document", "source_file": "C:\\programas\\3Dosim\\3Dosim_v4\\docs\\modulo_3\\vision_general.md", "source_location": "L141"}, {"id": "modulo_3_vision_general_paso_9_export_report_exportar_reporte_pdf", "label": "Paso 9: `export_report` \u2014 Exportar reporte PDF", "file_type": "document", "source_file": "C:\\programas\\3Dosim\\3Dosim_v4\\docs\\modulo_3\\vision_general.md", "source_location": "L145"}, {"id": "modulo_3_vision_general_paso_10_save_scene_guardar_escena_final", "label": "Paso 10: `save_scene` \u2014 Guardar escena final", "file_type": "document", "source_file": "C:\\programas\\3Dosim\\3Dosim_v4\\docs\\modulo_3\\vision_general.md", "source_location": "L155"}, {"id": "modulo_3_vision_general_3_dos_rutas_de_c\u00e1lculo_de_dosis", "label": "3. Dos Rutas de C\u00e1lculo de Dosis", "file_type": "document", "source_file": "C:\\programas\\3Dosim\\3Dosim_v4\\docs\\modulo_3\\vision_general.md", "source_location": "L161"}, {"id": "modulo_3_vision_general_4_entradas_y_salidas", "label": "4. Entradas y Salidas", "file_type": "document", "source_file": "C:\\programas\\3Dosim\\3Dosim_v4\\docs\\modulo_3\\vision_general.md", "source_location": "L175"}, {"id": "modulo_3_vision_general_5_archivos_de_c\u00f3digo", "label": "5. Archivos de C\u00f3digo", "file_type": "document", "source_file": "C:\\programas\\3Dosim\\3Dosim_v4\\docs\\modulo_3\\vision_general.md", "source_location": "L189"}, {"id": "modulo_3_vision_general_6_control_de_calidad_ai_supervisor", "label": "6. Control de Calidad (AI Supervisor)", "file_type": "document", "source_file": "C:\\programas\\3Dosim\\3Dosim_v4\\docs\\modulo_3\\vision_general.md", "source_location": "L207"}, {"id": "modulo_3_vision_general_7_referencias", "label": "7. Referencias", "file_type": "document", "source_file": "C:\\programas\\3Dosim\\3Dosim_v4\\docs\\modulo_3\\vision_general.md", "source_location": "L222"}], "edges": [{"source": "c_programas_3dosim_3dosim_v4_docs_modulo_3_vision_general_md", "target": "modulo_3_vision_general_visi\u00f3n_general_m\u00f3dulo_3_dosimetr\u00eda_interna_3d", "relation": "contains", "confidence": "EXTRACTED", "source_file": "C:\\programas\\3Dosim\\3Dosim_v4\\docs\\modulo_3\\vision_general.md", "source_location": "L1", "weight": 1.0}, {"source": "modulo_3_vision_general_visi\u00f3n_general_m\u00f3dulo_3_dosimetr\u00eda_interna_3d", "target": "modulo_3_vision_general_acr\u00f3nimos", "relation": "contains", "confidence": "EXTRACTED", "source_file": "C:\\programas\\3Dosim\\3Dosim_v4\\docs\\modulo_3\\vision_general.md", "source_location": "L5", "weight": 1.0}, {"source": "modulo_3_vision_general_visi\u00f3n_general_m\u00f3dulo_3_dosimetr\u00eda_interna_3d", "target": "modulo_3_vision_general_1_contexto_cl\u00ednico", "relation": "contains", "confidence": "EXTRACTED", "source_file": "C:\\programas\\3Dosim\\3Dosim_v4\\docs\\modulo_3\\vision_general.md", "source_location": "L28", "weight": 1.0}, {"source": "modulo_3_vision_general_visi\u00f3n_general_m\u00f3dulo_3_dosimetr\u00eda_interna_3d", "target": "modulo_3_vision_general_2_pipeline_de_10_pasos", "relation": "contains", "confidence": "EXTRACTED", "source_file": "C:\\programas\\3Dosim\\3Dosim_v4\\docs\\modulo_3\\vision_general.md", "source_location": "L45", "weight": 1.0}, {"source": "modulo_3_vision_general_2_pipeline_de_10_pasos", "target": "modulo_3_vision_general_codeblock_1", "relation": "contains", "confidence": "EXTRACTED", "source_file": "C:\\programas\\3Dosim\\3Dosim_v4\\docs\\modulo_3\\vision_general.md", "source_location": "L49", "weight": 1.0}, {"source": "modulo_3_vision_general_2_pipeline_de_10_pasos", "target": "modulo_3_vision_general_paso_1_load_scene_cargar_escena_desde_m\u00f3dulo_1", "relation": "contains", "confidence": "EXTRACTED", "source_file": "C:\\programas\\3Dosim\\3Dosim_v4\\docs\\modulo_3\\vision_general.md", "source_location": "L82", "weight": 1.0}, {"source": "modulo_3_vision_general_2_pipeline_de_10_pasos", "target": "modulo_3_vision_general_paso_2_read_pet_activity_leer_actividad_pet", "relation": "contains", "confidence": "EXTRACTED", "source_file": "C:\\programas\\3Dosim\\3Dosim_v4\\docs\\modulo_3\\vision_general.md", "source_location": "L90", "weight": 1.0}, {"source": "modulo_3_vision_general_2_pipeline_de_10_pasos", "target": "modulo_3_vision_general_paso_3_parse_mctal_parsear_archivo_mctal", "relation": "contains", "confidence": "EXTRACTED", "source_file": "C:\\programas\\3Dosim\\3Dosim_v4\\docs\\modulo_3\\vision_general.md", "source_location": "L94", "weight": 1.0}, {"source": "modulo_3_vision_general_2_pipeline_de_10_pasos", "target": "modulo_3_vision_general_paso_4_convert_to_dose_convertir_mev_cm3_a_gy", "relation": "contains", "confidence": "EXTRACTED", "source_file": "C:\\programas\\3Dosim\\3Dosim_v4\\docs\\modulo_3\\vision_general.md", "source_location": "L104", "weight": 1.0}, {"source": "modulo_3_vision_general_2_pipeline_de_10_pasos", "target": "modulo_3_vision_general_paso_5_compute_dvh_histograma_dosis_volumen", "relation": "contains", "confidence": "EXTRACTED", "source_file": "C:\\programas\\3Dosim\\3Dosim_v4\\docs\\modulo_3\\vision_general.md", "source_location": "L114", "weight": 1.0}, {"source": "modulo_3_vision_general_2_pipeline_de_10_pasos", "target": "modulo_3_vision_general_paso_6_compute_radiobiology_bed_eud_eqd2", "relation": "contains", "confidence": "EXTRACTED", "source_file": "C:\\programas\\3Dosim\\3Dosim_v4\\docs\\modulo_3\\vision_general.md", "source_location": "L122", "weight": 1.0}, {"source": "modulo_3_vision_general_2_pipeline_de_10_pasos", "target": "modulo_3_vision_general_paso_7_mird_partition_modelo_mird_de_partici\u00f3n", "relation": "contains", "confidence": "EXTRACTED", "source_file": "C:\\programas\\3Dosim\\3Dosim_v4\\docs\\modulo_3\\vision_general.md", "source_location": "L132", "weight": 1.0}, {"source": "modulo_3_vision_general_2_pipeline_de_10_pasos", "target": "modulo_3_vision_general_paso_8_visualize_slicer_visualizaci\u00f3n_en_3d_slicer", "relation": "contains", "confidence": "EXTRACTED", "source_file": "C:\\programas\\3Dosim\\3Dosim_v4\\docs\\modulo_3\\vision_general.md", "source_location": "L141", "weight": 1.0}, {"source": "modulo_3_vision_general_2_pipeline_de_10_pasos", "target": "modulo_3_vision_general_paso_9_export_report_exportar_reporte_pdf", "relation": "contains", "confidence": "EXTRACTED", "source_file": "C:\\programas\\3Dosim\\3Dosim_v4\\docs\\modulo_3\\vision_general.md", "source_location": "L145", "weight": 1.0}, {"source": "modulo_3_vision_general_2_pipeline_de_10_pasos", "target": "modulo_3_vision_general_paso_10_save_scene_guardar_escena_final", "relation": "contains", "confidence": "EXTRACTED", "source_file": "C:\\programas\\3Dosim\\3Dosim_v4\\docs\\modulo_3\\vision_general.md", "source_location": "L155", "weight": 1.0}, {"source": "modulo_3_vision_general_visi\u00f3n_general_m\u00f3dulo_3_dosimetr\u00eda_interna_3d", "target": "modulo_3_vision_general_3_dos_rutas_de_c\u00e1lculo_de_dosis", "relation": "contains", "confidence": "EXTRACTED", "source_file": "C:\\programas\\3Dosim\\3Dosim_v4\\docs\\modulo_3\\vision_general.md", "source_location": "L161", "weight": 1.0}, {"source": "modulo_3_vision_general_visi\u00f3n_general_m\u00f3dulo_3_dosimetr\u00eda_interna_3d", "target": "modulo_3_vision_general_4_entradas_y_salidas", "relation": "contains", "confidence": "EXTRACTED", "source_file": "C:\\programas\\3Dosim\\3Dosim_v4\\docs\\modulo_3\\vision_general.md", "source_location": "L175", "weight": 1.0}, {"source": "modulo_3_vision_general_visi\u00f3n_general_m\u00f3dulo_3_dosimetr\u00eda_interna_3d", "target": "modulo_3_vision_general_5_archivos_de_c\u00f3digo", "relation": "contains", "confidence": "EXTRACTED", "source_file": "C:\\programas\\3Dosim\\3Dosim_v4\\docs\\modulo_3\\vision_general.md", "source_location": "L189", "weight": 1.0}, {"source": "modulo_3_vision_general_visi\u00f3n_general_m\u00f3dulo_3_dosimetr\u00eda_interna_3d", "target": "modulo_3_vision_general_6_control_de_calidad_ai_supervisor", "relation": "contains", "confidence": "EXTRACTED", "source_file": "C:\\programas\\3Dosim\\3Dosim_v4\\docs\\modulo_3\\vision_general.md", "source_location": "L207", "weight": 1.0}, {"source": "modulo_3_vision_general_visi\u00f3n_general_m\u00f3dulo_3_dosimetr\u00eda_interna_3d", "target": "modulo_3_vision_general_7_referencias", "relation": "contains", "confidence": "EXTRACTED", "source_file": "C:\\programas\\3Dosim\\3Dosim_v4\\docs\\modulo_3\\vision_general.md", "source_location": "L222", "weight": 1.0}], "input_tokens": 0, "output_tokens": 0}